kaaas/__init__.py
kaaas/config.py
kaaas/main.py
kaaas/utils.py
kaaas/pyarmor_runtime_000000/__init__.py
kaaas/pyarmor_runtime_000000/pyarmor_runtime.so
kaaas/pyarmor_runtime_000000/__pycache__/__init__.cpython-311.pyc
kaaas-0.1.2.dist-info/licenses/LICENSE
kaaas-0.1.2.dist-info/METADATA
kaaas-0.1.2.dist-info/WHEEL
kaaas-0.1.2.dist-info/entry_points.txt
kaaas-0.1.2.dist-info/top_level.txt
kaaas-0.1.2.dist-info/RECORD
