Metadata-Version: 2.4
Name: kaaas
Version: 0.1.2
Summary: Kubernetes AI-powered Cluster Analysis and Solution (KAAAS)
Home-page: https://github.com/yourusername/kaaas
Author: Kashif Rafi
Author-email: rafi.kashif@yahoo.com
License: Proprietary
Keywords: kubernetes,ai,cluster,analysis,k8sgpt,llm
Classifier: Programming Language :: Python :: 3
Classifier: License :: OSI Approved :: MIT License
Classifier: Operating System :: OS Independent
Classifier: Topic :: System :: Monitoring
Classifier: Topic :: Software Development :: Libraries :: Python Modules
Requires-Python: >=3.6
License-File: LICENSE
Requires-Dist: boto3
Requires-Dist: pyyaml
Dynamic: author
Dynamic: author-email
Dynamic: classifier
Dynamic: description
Dynamic: description-content-type
Dynamic: home-page
Dynamic: keywords
Dynamic: license
Dynamic: license-file
Dynamic: requires-dist
Dynamic: requires-python
Dynamic: summary
